cpm_analytics/__init__.py
cpm_analytics/main.py
cpm_analytics/src/compute_score.py
cpm_analytics/src/encode_categorical_variables.py
cpm_analytics/src/plot_heatmap.py
cpm_analytics/src/plot_variables_relationship.py
cpm_analytics/src/summary_report.py
cpm_analytics/src/supporting_functions.py
cpm_analytics-0.0.204.dist-info/LICENSE
cpm_analytics-0.0.204.dist-info/METADATA
cpm_analytics-0.0.204.dist-info/WHEEL
cpm_analytics-0.0.204.dist-info/top_level.txt
cpm_analytics-0.0.204.dist-info/RECORD
