Metadata-Version: 2.1
Name: cpm-analytics
Version: 0.0.204
Summary: Investigate relationship on variables pairs in tabular datasets, based on Correlation, PPS and MIC scores.
Author: Fernando Stefankevicius
Author-email: fernando_doreto@hotmail.com
License: MIT
Project-URL: Bug Tracker, https://github.com/
Classifier: Programming Language :: Python :: 3.8
Classifier: License :: OSI Approved :: MIT License
Classifier: Operating System :: OS Independent
License-File: LICENSE
Requires-Dist: pandas (==1.3.5)
Requires-Dist: matplotlib (==3.5.0)
Requires-Dist: seaborn (==0.11.2)
Requires-Dist: ppscore (==1.3.0)
Requires-Dist: minepy (==1.2.6)
Requires-Dist: feature-engine (==1.4.0)
Requires-Dist: scikit-learn (==1.1.1)
